poppo213/__init__.py
poppo213/links.txt
poppo213/poppo213.py
poppo213-1.7.dist-info/METADATA
poppo213-1.7.dist-info/WHEEL
poppo213-1.7.dist-info/entry_points.txt
poppo213-1.7.dist-info/top_level.txt
poppo213-1.7.dist-info/RECORD
