Metadata-Version: 2.4
Name: poppo213
Version: 1.7
Requires-Dist: requests
Dynamic: requires-dist
